pytest_pusher/__init__.py
pytest_pusher/core.py
pytest_pusher-0.0.3.dist-info/LICENSE
pytest_pusher-0.0.3.dist-info/METADATA
pytest_pusher-0.0.3.dist-info/WHEEL
pytest_pusher-0.0.3.dist-info/entry_points.txt
pytest_pusher-0.0.3.dist-info/top_level.txt
pytest_pusher-0.0.3.dist-info/RECORD
